coloredlogs.pth
coloredlogs/__init__.py
coloredlogs/cli.py
coloredlogs/demo.py
coloredlogs/syslog.py
coloredlogs/tests.py
coloredlogs/converter/__init__.py
coloredlogs/converter/colors.py
coloredlogs-14.3.dist-info/LICENSE.txt
coloredlogs-14.3.dist-info/METADATA
coloredlogs-14.3.dist-info/WHEEL
coloredlogs-14.3.dist-info/entry_points.txt
coloredlogs-14.3.dist-info/top_level.txt
coloredlogs-14.3.dist-info/RECORD
